Workbook

Sheet DataTypeMaker
A1: DATATYPE | B1: List of Static Values | C1: List.. | D1: List.. | G1: Y/N Box | J1: Quantity
A2: For Model Maker | B2: =B3&B4&B5&B6 -> L#Qualification=Phd/Masters/Bachelor/Diploma/Certificate | C2: =C3&C4&C5&C6 -> L#ContractType=Permanent/Contract/Temporary/OneTime/Impromptu | D2: =D3&D4&D5&D6 -> L#PaidBy=Hourly/Daily/Monthly/Project/Adhoc | E2: =E3&E4&E5&E6 -> L#TrainingType=InHouse/Outsourced/Academy/Adhoc | F2: =F3&F4&F5&F6 -> L#Performance=Excellent/Good/Fair/Poor | G2: =G3&G4&G5 -> Y#Certified | H2: =H3&H4&H5 -> Y#YearsExperience | I2: =I3&I4&I5 -> Y#Registered | J2: =J3&J4&J5 -> Q#NoOfDays | K2: =K3&K4&K5 -> Q#NoOfHours
A3: DataTypeCode | B3: L# | C3: L# | D3: L# | E3: L# | F3: L# | G3: Y# | H3: Y# | I3: =H3 -> Y# | J3: Q# | K3: Q#
A4: Name | B4: Qualification | C4: ContractType | D4: PaidBy | E4: TrainingType | F4: Performance | G4: Certified | H4: YearsExperience | I4: Registered | J4: NoOfDays | K4: NoOfHours
B5: ="=" -> = | C5: ="=" -> = | D5: ="=" -> = | E5: ="=" -> = | F5: ="=" -> =
A6: List Values | B6: =_xlfn.TEXTJOIN("/", ,B7:B11) -> Phd/Masters/Bachelor/Diploma/Certificate | C6: =_xlfn.TEXTJOIN("/", ,C7:C11) -> Permanent/Contract/Temporary/OneTime/Impromptu | D6: =_xlfn.TEXTJOIN("/", ,D7:D11) -> Hourly/Daily/Monthly/Project/Adhoc | E6: =_xlfn.TEXTJOIN("/", ,E7:E10) -> InHouse/Outsourced/Academy/Adhoc | F6: =_xlfn.TEXTJOIN("/", ,F7:F10) -> Excellent/Good/Fair/Poor
A7: 1st | B7: Phd | C7: Permanent | D7: Hourly | E7: InHouse | F7: Excellent
A8: 2nd | B8: Masters | C8: Contract | D8: Daily | E8: Outsourced | F8: Good
A9: 3rd | B9: Bachelor | C9: Temporary | D9: Monthly | E9: Academy | F9: Fair
A10: 4th | B10: Diploma | C10: OneTime | D10: Project | E10: Adhoc | F10: Poor
A11: 5th | B11: Certificate | C11: Impromptu | D11: Adhoc | E11: Free

Sheet 1_RO_ModelHeader
A1: Name | B1: Version
A2: HRMIS | B2: 1

Sheet 2_RO_ModelMaker
A1: RO_ModelHeader_ID | B1: SeqNo | C1: WorkflowStructure | D1: KanbanBoard | E1: Master | F1: Name | G1: Help | H1: ColumnSet
A2: HRMIS | B2: 1 | C2: N | D2: N | F2: HR_Terminology | G2: Preset DataTypes that shall be used later on. Ninja Excel : DataTypeMaker | H2: =_xlfn.TEXTJOIN(",",,DataTypeMaker!B2:T2) -> L#Qualification=Phd/Masters/Bachelor/Diploma/Certificate,L#ContractType=Permanent/Contract/Temporary/OneTime/Impromptu,L#PaidBy=Hourly/Daily/Monthly/Project/Adhoc,L#TrainingType=InHouse/Outsourced/Academy/Adhoc,L#Performance=Excellent/Good/Fair/Poor,Y#Certified,Y#YearsExperience,Y#Registered,Q#NoOfDays,Q#NoOfHours,,,,,,,,,
A3: HRMIS | B3: 2 | C3: N | D3: N | F3: =ModelMakerSource!A2 -> HR_HumanResourceManagement | G3: Main Tab,C_Bpartner_ID>Company | H3: =_xlfn.TEXTJOIN(",",,ModelMakerSource!A3:A6) -> Name,C_Bpartner_ID,C_Bpartner_Location_ID,AD_ClientInfo
A4: HRMIS | B4: 3 | C4: N | D4: N | E4: =ModelMakerSource!B1 -> HR_HumanResourceManagement | F4: =ModelMakerSource!B2 -> HR_JobDesignation | G4: HR Job Descriptions, AD_User_ID>Substitute | H4: =_xlfn.TEXTJOIN(",",,ModelMakerSource!B3:B10) -> Name,Description,Qualification,YearsExperience,Training,Experience,AD_User_ID,
A5: HRMIS | B5: 4 | C5: N | D5: N | E5: =ModelMakerSource!C1 -> HR_HumanResourceManagement | F5: =ModelMakerSource!C2 -> HR_Trainer | G5: Trainer Details. C_Bpartner_ID>Trainer | H5: =_xlfn.TEXTJOIN(",",,ModelMakerSource!C3:C9) -> Name,C_Bpartner_ID,Description,C_Location_ID,Registered,,
A6: HRMIS | B6: 5 | C6: N | D6: N | E6: =ModelMakerSource!D1 -> HR_HumanResourceManagement | F6: =ModelMakerSource!D2 -> HR_Rank | G6: Rank Details | H6: =_xlfn.TEXTJOIN(",",,ModelMakerSource!D3:D10) -> Name,Description,Before,After,Title,Prerequisite,,
A7: HRMIS | B7: 6 | C7: N | D7: N | E7: =ModelMakerSource!E1 -> HR_HumanResourceManagement | F7: =ModelMakerSource!E2 -> HR_TrainingCourse | G7: Type of Training | H7: =_xlfn.TEXTJOIN(",",,ModelMakerSource!E3:E10) -> Name,Description,HR_Trainer_ID,TrainingType,Certified,Qualification,Registered,
A8: HRMIS | B8: 7 | C8: N | D8: N | E8: =ModelMakerSource!F1 -> HR_HumanResourceManagement | F8: =ModelMakerSource!F2 -> HR_ManpowerRequirement | G8: Manpower Requirement and Vacancy Status,AD_Org_ID>Department | H8: =_xlfn.TEXTJOIN(",",,ModelMakerSource!F3:F10) -> Name,Description,HR_JobDesignation,QtyOnHand,QtyNeeded,DateStart,DateEnd,
A9: HRMIS | B9: 8 | C9: N | D9: N | E9: =ModelMakerSource!G1 -> HR_HumanResourceManagement | F9: =ModelMakerSource!G2 -> HR_ProjectTaskForce | G9: Type of Training | H9: =_xlfn.TEXTJOIN(",",,ModelMakerSource!G3:G10) -> Name,Description,C_Project_ID,C_Campaign_ID,DateStart,DateEnd,QtyPersonnel,
A10: HRMIS | B10: 9 | C10: N | D10: N | E10: =ModelMakerSource!H1 -> HR_HumanResourceManagement | F10: =ModelMakerSource!H2 -> HR_EmployeeProvidentFund | G10: Manpower Requirement and Vacancy Status,AD_Org_ID>Department | H10: =_xlfn.TEXTJOIN(",",,ModelMakerSource!H3:H10) -> Name,Value,C_BPartner_ID,AccountNote,EPFNote,,,
A11: HRMIS | B11: 10 | C11: N | D11: N | F11: =ModelMakerSource!I2 -> HR_Employment | G11: Current Employment. Additional to AD_User record,AD_User_ID>Superior | H11: =_xlfn.TEXTJOIN(",",,ModelMakerSource!I4:I18) -> C_BPartner_ID,Description,ContractType,PaidBy,AD_User_ID,DateStart,C_BPartner_ID,HR_JobDesignation_ID,Position,Contact,Q#BasicPay,HR_Rank_ID,HR_EmployeeProvidentFund_ID,,
A12: HRMIS | B12: 11 | C12: N | D12: N | E12: =ModelMakerSource!J1 -> HR_Employment | F12: =ModelMakerSource!J2 -> HR_EmploymentHistory | G12: History of Employee | H12: =_xlfn.TEXTJOIN(",",,ModelMakerSource!J3:J17) -> Name,Description,ContractType,PaidBy,AD_User_ID,DateStart,DateEnd,HR_JobDesignation_ID,Position,Contact,T#ExitInterview,BasicPay,HR_Rank_ID,,
A13: HRMIS | B13: 12 | C13: N | D13: N | E13: =ModelMakerSource!K1 -> HR_Employment | F13: =ModelMakerSource!K2 -> HR_MedicalHIstory | G13: Medical History | H13: =_xlfn.TEXTJOIN(",",,ModelMakerSource!K3:K17) -> Name,Description,MedicalTest,Treatment,Diagnosis,DateDone,Admission,Doctor,DateEnd,Surgery,Allergy,Price,HospitalClinic,,
A14: HRMIS | B14: 13 | C14: N | D14: N | E14: =ModelMakerSource!L1 -> HR_Employment | F14: =ModelMakerSource!L2 -> HR_Payroll | G14: Payorll | H14: =_xlfn.TEXTJOIN(",",,ModelMakerSource!L3:L17) -> Name,Value,Description,Paid,C_Period_ID,ChequeNo,Q#Earnings,Q#Deductions,GrandTotal,DateIssued,DatePayment,C_Invoice_ID,,,
A15: HRMIS | B15: 14 | C15: N | D15: N | E15: =ModelMakerSource!M1 -> HR_Payroll | F15: =ModelMakerSource!M2 -> HR_PayrollDetails | G15: Payroll Details | H15: =_xlfn.TEXTJOIN(",",,ModelMakerSource!M3:M17) -> PayrollCode,Q#Earnings,Q#Deductions,LineNetAmt,Remarks,,,,,,,,,,
A16: HRMIS | B16: 15 | C16: N | D16: N | E16: =ModelMakerSource!N1 -> HR_Employment | F16: =ModelMakerSource!N2 -> HR_FamilyMembers | G16: Family Members | H16: =_xlfn.TEXTJOIN(",",,ModelMakerSource!N3:N17) -> Name,Value,Description,Relationship,ContactNo,C_Location_ID,Y#NextOfKin,Relationship,,,,,,,
A17: HRMIS | B17: 16 | C17: N | D17: N | E17: =ModelMakerSource!O1 -> HR_Employment | F17: =ModelMakerSource!O2 -> HR_Appraisal | G17: Appraisal | H17: =_xlfn.TEXTJOIN(",",,ModelMakerSource!O3:O17) -> Name,Description,DateTaken,C_BPartner_ID,T#ExpertAnalysis,Performance,Y#Promoted,QtyIncrement,T#Remarks,Amount,,,,,
A18: HRMIS | B18: 17 | C18: N | D18: N | E18: =ModelMakerSource!P1 -> HR_Employment | F18: =ModelMakerSource!P2 -> HR_Training | G18: Training Record History | H18: =_xlfn.TEXTJOIN(",",,ModelMakerSource!P3:P17) -> Name,Description,HR_TrainingCourse_ID,DateStart,DateEnd,,,,,,,,,,
A19: HRMIS | B19: 18 | C19: N | D19: N | E19: =ModelMakerSource!Q1 -> HR_Employment | F19: =ModelMakerSource!Q2 -> HR_LeaveApplication | G19: Leave Application and Status | H19: =_xlfn.TEXTJOIN(",",,ModelMakerSource!Q3:Q17) -> Name,Description,DateRequested,DateStart,DateEnd,Approved,AD_User_ID,C_BPartner_ID,Qualified,Memo,Substitute,,,,
A20: HRMIS | B20: 19 | C20: N | D20: N | E20: =E19 -> HR_Employment | F20: =ModelMakerSource!R2 -> HR_AssistanceRequest | G20: Assistance Request, tie to CRM Request model | H20: =_xlfn.TEXTJOIN(",",,ModelMakerSource!R3:R17) -> Name,Description,DateRequested,R_RequestType_ID,Amount,Approved,AD_User_ID,C_BPartner_ID,Period,R_Request_ID,Result,,,,

Sheet 3_RO_CodeMaker
A1: RO_ModelHeader_ID | B1: SeqNo | C1: Name | D1: PluginLocation | E1: GenerateModel | F1: GenerateModelFactory | G1: GenerateProcess | H1: Description | I1: ProcessParameters
A2: =1_RO_ModelHeader!A2 -> HRMIS | B2: 1 | C2: =2_RO_ModelMaker!F12 -> HR_EmploymentHistory | D2: /usr/local/org.red1.blank/src/ | E2: Y | F2: Y | G2: MY_Process | I2: IsActive

Sheet 4_AD_Package_Exp
A1: Name | B1: AD_Client_ID | C1: AD_Org_ID | D1: PK_Version
A2: =1_RO_ModelHeader!A2 -> HRMIS | B2: System | C2: * | D2: 1

Sheet 5_AD_Package_Exp_Detail
A1: AD_Package_Exp_ID | B1: Type | C1: AD_Client_ID | D1: AD_Org_ID | E1: AD_Menu_ID | F1: AD_Table_ID | G1: SQLStatement | H1: Description
A2: =4_AD_Package_Exp!A2 -> HRMIS | B2: M | C2: =4_AD_Package_Exp!B2 -> System | D2: =4_AD_Package_Exp!C2 -> * | E2: New Menu | F2: Package Exp. | G2: SELECT * FROM AD_Package_Exp WHERE NAME = ' | H2: ‘;AD_Package_Exp_Detail
A3: =A2 -> HRMIS | B3: D | C3: =C2 -> System | D3: =D2 -> * | E3: =E2 -> New Menu | F3: Package Exp. | G3: =CONCATENATE(G2,A2,H2) -> SELECT * FROM AD_Package_Exp WHERE NAME = 'HRMIS‘;AD_Package_Exp_Detail | H3: blank

Sheet C_BPartner
A1: Name | B1: Value | C1: IsEmployee | D1: C_BP_Group_ID
A2: ABU ALIMIN BIN ABU KASSIM | B2: 34536345 | C2: Y | D2: Employees
A3: ADRYNNA LAILY BINTI ARIS AZMIL | B3: 33553115 | C3: Y | D3: Employees
A4: AHMAD ISKANDAR BIN ZAINON | B4: 31565637 | C4: Y | D4: Employees
A5: AHMAD ZARIF MIKHAIL BIN AHMAD ZAKRI | B5: 34536346 | C5: Y | D5: Employees
A6: AINI NATASYA BINTI MAS WIRA | B6: 33553116 | C6: Y | D6: Employees
A7: AKMAL ZAKWAN BIN MOHD ALI | B7: 31565638 | C7: Y | D7: Employees
A8: IRDINA ADLIN BINTI IRWAN ASRAN | B8: 34536347 | C8: Y | D8: Employees
A9: KARTIGA A/P BALAMURLY | B9: 33553117 | C9: Y | D9: Employees
A10: KOSHANRAJ A/L INTHERAN | B10: 31565639 | C10: Y | D10: Employees
A11: MOHAMAD AIMAN NAJMI BIN MOHD ANUAR | B11: 34536348 | C11: Y | D11: Employees
A12: MUHAMAD ADAM DANIAL BIN AZMI | B12: 33553118 | C12: Y | D12: Employees
A13: MUHAMMAD AIMAN AZIZI BIN MOHD AZMAN | B13: 31565640 | C13: Y | D13: Employees
... A32: YAAGAVIEE A/P SILVAM | B32: 34536347 | C32: Y | D32: Employees

Sheet ModelMakerSource
B1: =A2 -> HR_HumanResourceManagement | C1: =A2 -> HR_HumanResourceManagement | D1: =A2 -> HR_HumanResourceManagement | E1: =A2 -> HR_HumanResourceManagement | F1: =A2 -> HR_HumanResourceManagement | G1: =F1 -> HR_HumanResourceManagement | H1: =G1 -> HR_HumanResourceManagement | J1: =I2 -> HR_Employment | K1: =I2 -> HR_Employment | L1: =J1 -> HR_Employment | M1: =L2 -> HR_Payroll | N1: =J1 -> HR_Employment | O1: =N1 -> HR_Employment | P1: =N1 -> HR_Employment | Q1: =N1 -> HR_Employment | R1: =N1 -> HR_Employment
A2: HR_HumanResourceManagement | B2: HR_JobDesignation | C2: HR_Trainer | D2: HR_Rank | E2: HR_TrainingCourse | F2: HR_ManpowerRequirement | G2: HR_ProjectTaskForce | H2: HR_EmployeeProvidentFund | I2: HR_Employment | J2: HR_EmploymentHistory | K2: HR_MedicalHIstory | L2: HR_Payroll | M2: HR_PayrollDetails | N2: HR_FamilyMembers | O2: HR_Appraisal | P2: HR_Training | Q2: HR_LeaveApplication | R2: HR_AssistanceRequest
A3: Name | B3: Name | C3: Name | D3: Name | E3: Name | F3: Name | G3: Name | H3: Name | I3: Name | J3: Name | K3: Name | L3: Name | M3: PayrollCode | N3: Name | O3: Name | P3: Name | Q3: Name | R3: Name
A4: C_Bpartner_ID | B4: Description | C4: C_Bpartner_ID | D4: Description | E4: Description | F4: Description | G4: Description | H4: Value | I4: ="C_BPartner_ID" -> C_BPartner_ID | J4: Description | K4: Description | L4: Value | M4: Q#Earnings | N4: Value | O4: Description | P4: Description | Q4: Description | R4: Description
A5: C_Bpartner_Location_ID | B5: =DataTypeMaker!B4 -> Qualification | C5: Description | D5: Before | E5: =C2&"_ID" -> HR_Trainer_ID | F5: =B2 -> HR_JobDesignation | G5: C_Project_ID | H5: ="C_BPartner_ID" -> C_BPartner_ID | I5: Description | J5: =I6 -> ContractType | K5: MedicalTest | L5: Description | M5: Q#Deductions | N5: Description | O5: DateTaken | P5: =E2&"_ID" -> HR_TrainingCourse_ID | Q5: DateRequested | R5: DateRequested
A6: AD_ClientInfo | B6: YearsExperience | C6: C_Location_ID | D6: After | E6: =DataTypeMaker!E4 -> TrainingType | F6: QtyOnHand | G6: C_Campaign_ID | H6: AccountNote | I6: =DataTypeMaker!C4 -> ContractType | J6: =DataTypeMaker!D4 -> PaidBy | K6: Treatment | L6: Paid | M6: LineNetAmt | N6: Relationship | O6: ="C_BPartner_ID" -> C_BPartner_ID | P6: DateStart | Q6: DateStart | R6: R_RequestType_ID
B7: Training | C7: Registered | D7: Title | E7: =DataTypeMaker!G4 -> Certified | F7: QtyNeeded | G7: DateStart | H7: EPFNote | I7: =DataTypeMaker!D4 -> PaidBy | J7: AD_User_ID | K7: Diagnosis | L7: C_Period_ID | M7: Remarks | N7: ContactNo | O7: T#ExpertAnalysis | P7: DateEnd | Q7: DateEnd | R7: Amount
B8: Experience | D8: Prerequisite | E8: =DataTypeMaker!B4 -> Qualification | F8: DateStart | G8: DateEnd | I8: AD_User_ID | J8: DateStart | K8: DateDone | L8: ChequeNo | N8: C_Location_ID | O8: =DataTypeMaker!F4 -> Performance | Q8: Approved | R8: Approved
B9: AD_User_ID | E9: =DataTypeMaker!I4 -> Registered | F9: DateEnd | G9: QtyPersonnel | I9: DateStart | J9: DateEnd | K9: Admission | L9: Q#Earnings | N9: Y#NextOfKin | O9: Y#Promoted | Q9: AD_User_ID | R9: AD_User_ID
I10: ="C_BPartner_ID" -> C_BPartner_ID | J10: =I11 -> HR_JobDesignation_ID | K10: Doctor | L10: Q#Deductions | N10: Relationship | O10: QtyIncrement | Q10: ="C_BPartner_ID" -> C_BPartner_ID | R10: ="C_BPartner_ID" -> C_BPartner_ID
I11: =B2&"_ID" -> HR_JobDesignation_ID | J11: Position | K11: DateEnd | L11: GrandTotal | O11: T#Remarks | Q11: Qualified | R11: Period
I12: Position | J12: Contact | K12: Surgery | L12: DateIssued | O12: Amount | Q12: Memo | R12: R_Request_ID
I13: Contact | J13: T#ExitInterview | K13: Allergy | L13: DatePayment | Q13: Substitute | R13: Result
I14: Q#BasicPay | J14: BasicPay | K14: Price | L14: C_Invoice_ID
I15: =D2&"_ID" -> HR_Rank_ID | J15: =D2&"_ID" -> HR_Rank_ID | K15: HospitalClinic
I16: =H2&"_ID" -> HR_EmployeeProvidentFund_ID

Sheet HR_HumanResourceManagement
A1: Name | B1: C_Bpartner_ID | C1: C_Bpartner_Location_ID

Sheet HR_JobDesignation
A1: Name | B1: Description | C1: Qualification | D1: YearsExperience | E1: Training | F1: Experience | G1: AD_User_ID

Sheet HR_Trainer


Sheet HR_Rank_ID


Sheet HR_TrainingType

Sheet HR_ManpowerRequirement

Sheet HR_EmploymentHistory

Sheet HR_Appraisal

Sheet HR_Training

Sheet HR_LeaveApplication
